zippy/__init__.py
zippy/_zippy_data.cp311-win_amd64.pyd
zippy/arrow_compat.py
zippy/dataset.py
zippy/duckdb_compat.py
zippy/fast_store.py
zippy/hub.py
zippy/iterable_dataset.py
zippy/json_backend.py
zippy/pandas_compat.py
zippy/providers/__init__.py
zippy/providers/base.py
zippy/providers/git.py
zippy/providers/stubs.py
zippy/root.py
zippy/store.py
zippy/utils.py
zippy_data-0.1.2.dist-info/METADATA
zippy_data-0.1.2.dist-info/WHEEL
zippy_data-0.1.2.dist-info/RECORD
