Metadata-Version: 2.4
Name: zippy-data
Version: 0.1.2
Classifier: Development Status :: 3 - Alpha
Classifier: Intended Audience :: Developers
Classifier: Intended Audience :: Science/Research
Classifier: License :: OSI Approved :: Apache Software License
Classifier: License :: OSI Approved :: MIT License
Classifier: Programming Language :: Python :: 3
Classifier: Programming Language :: Python :: 3.9
Classifier: Programming Language :: Python :: 3.10
Classifier: Programming Language :: Python :: 3.11
Classifier: Programming Language :: Python :: 3.12
Classifier: Programming Language :: Rust
Classifier: Topic :: Scientific/Engineering :: Artificial Intelligence
Requires-Dist: pandas>=1.0 ; extra == 'pandas'
Requires-Dist: pyarrow>=10.0 ; extra == 'arrow'
Requires-Dist: duckdb>=0.8 ; extra == 'duckdb'
Requires-Dist: datasets>=2.0 ; extra == 'hf'
Requires-Dist: pandas>=1.0 ; extra == 'all'
Requires-Dist: pyarrow>=10.0 ; extra == 'all'
Requires-Dist: duckdb>=0.8 ; extra == 'all'
Requires-Dist: datasets>=2.0 ; extra == 'all'
Requires-Dist: pytest>=7.0 ; extra == 'dev'
Requires-Dist: pytest-cov ; extra == 'dev'
Requires-Dist: mypy ; extra == 'dev'
Requires-Dist: ruff ; extra == 'dev'
Requires-Dist: datasets>=2.0 ; extra == 'dev'
Provides-Extra: pandas
Provides-Extra: arrow
Provides-Extra: duckdb
Provides-Extra: hf
Provides-Extra: all
Provides-Extra: dev
Summary: High-performance, multi-language dataset storage format
Keywords: dataset,storage,ml,ai,huggingface
Author-email: Omneity Labs <zippy@omarkama.li>
License: Apache-2.0 OR MIT
Requires-Python: >=3.9
Project-URL: Homepage, https://zippydata.org
Project-URL: Repository, https://github.com/zippydata/zippy
Project-URL: Documentation, https://zippydata.org/docs
